kruz/__init__.py
kruz/__main__.py
kruz/__version__.py
kruz/access_code.py
kruz/file_transfer_tcp.py
kruz/settings.py
octo/__init__.py
octo/__main__.py
octo/__version__.py
octo/file_transfer.py
octo/file_transfer_tcp.py
octo/file_transfer_udp.py
octo/filerecver.py
octo/filesender.py
octo/settings.py
octo/stun.py
tests/__init__.py
tests/test_argparse.py
tests/test_file_transfer.py
tests/test_fileio.py
tests/test_filerecver.py
tests/test_filesender.py
tests/test_ipv6.py
kruz-0.0.4.dist-info/LICENSE
kruz-0.0.4.dist-info/METADATA
kruz-0.0.4.dist-info/WHEEL
kruz-0.0.4.dist-info/entry_points.txt
kruz-0.0.4.dist-info/top_level.txt
kruz-0.0.4.dist-info/RECORD
